{
  "id": "PPL_LUO_PAGU",
  "nameMain": "Luo Pagu",
  "languageFamilyId": "FLG_NILOTIQUE",
  "currentCountries": ["UGA", "KEN"],
  "content": {
    "appellations": {
      "mainName": "Luo Pagu",
      "selfAppellation": "Luo Pagu",
      "exonyms": ["Luo Pagu (terme utilisé par les Européens)"],
      "linguisticFamily": "FLG_NILOTIQUE",
      "ethnoLinguisticGroup": "Nilotique occidental",
      "historicalRegion": "UGA, KEN",
      "currentCountries": ["UGA", "KEN"]
    },
    "ethnicities": [
      "Luo Pagu d'Ouganda",
      "Luo Pagu du Kenya",
      "Sous-groupes régionaux"
    ],
    "origins": {
      "ancientOrigins": "Les Luo Pagu sont originaires de l'Ouganda et du Kenya. Leur présence dans la région remonte à plusieurs siècles. Ils font partie du groupe nilotique occidental (Luo).",
      "unificationsOrDivisions": "Organisation en groupes territoriaux distincts mais partageant une identité culturelle et linguistique commune avec les autres groupes Luo.",
      "externalInfluences": "Contacts avec les peuples bantous, influence du christianisme."
    },
    "organization": {
      "traditionalPoliticalSystem": "Organisation en chefferies traditionnelles. Système de conseils d'anciens pour la gouvernance.",
      "clanOrganization": "Structure clanique patrilinéaire. Organisation en familles étendues et lignages.",
      "roleOfLineages": "Lignages patrilinéaires déterminant l'identité et les alliances.",
      "religiousAuthority": "Autorité des chefs religieux traditionnels et des pasteurs chrétiens. Syncrétisme religieux."
    },
    "languages": {
      "mainLanguage": "Luo (dialecte Pagu)",
      "vehicularRole": "Le luo pagu est parlé par la majorité des Luo Pagu. Le swahili, l'anglais et d'autres langues sont également utilisés."
    },
    "culture": {
      "Rites majeurs": "",
      "source_0": "Cérémonies de mariage traditionnelles",
      "source_1": "Rites de passage (initiation, fêtes de naissance)",
      "source_2": "Cérémonies liées à l'agriculture et à l'élevage",
      "source_3": "Cérémonies religieuses chrétiennes",
      "Symboles": "Symboles liés à l'agriculture et à l'élevage, symboles culturels luo, symboles chrétiens.",
      "Arts et musique": "",
      "source_4": "Musique traditionnelle",
      "source_5": "Danse traditionnelle",
      "source_6": "Poésie orale",
      "source_7": "Artisanat (poterie, tissage)",
      "Spiritualités": "Syncrétisme entre croyances traditionnelles et christianisme. Rôle important des ancêtres."
    },
    "historicalRole": {
      "kingdomsOrChiefdoms": "",
      "relationsWithNeighbors": "",
      "conflictsOrAlliances": "",
      "diaspora": "Diaspora luo pagu dans les grandes villes ougandaises et kényanes, et dans les pays occidentaux."
    },
    "demography": {
      "totalPopulation": 300000,
      "referenceYear": 2025,
      "source": "Estimations basées sur recensements, SIL Ethnologue, et études démographiques"
    },
    "sources": [
      "SIL Ethnologue – Luo language (luo)",
      "CIA World Factbook – Uganda, KEN",
      "Recensements nationaux",
      "Études anthropologiques sur les peuples nilotiques"
    ]
  }
}
