{
  "id": "PPL_FON",
  "nameMain": "",
  "languageFamilyId": "FLG_BENOUECONGO",
  "currentCountries": ["TGO"],
  "content": {
    "appellations": {
      "mainName": "",
      "selfAppellation": "Fɔ̀ngbè / Fon",
      "linguisticFamily": "FLG_BENOUECONGO",
      "currentCountries": ["TGO"]
    },
    "ethnicities": [],
    "origins": null,
    "organization": null,
    "languages": null,
    "culture": null,
    "historicalRole": null,
    "demography": null,
    "sources": ["Ethnologue (fon)", "Archives du Royaume d’Abomey"]
  }
}
